{
  "title": "Lights, Camera, Reaction!",
  "review_score_100": 71,
  "max_players": 9,
  "platforms": [
    "Windows"
  ],
  "review_sources": [
    "https://store.steampowered.com/app/1222000/Lights_Camera_Reaction/"
  ],
  "notes": "Steam describes VR + non‑VR multiplayer (phone or keyboard/controller) and shows 6 user reviews. Play mode inferred from description.",
  "raw_comment": "VR + local multiplayer mini game based party game. 2-6 players in VR + keyboard/controller mode. 4-9 players in VR + smartphone mode. Separate screens.",
  "last_updated": "2025-12-29",
  "screen_mode": "separate",
  "play_mode": "simultaneous",
  "input_methods": [
    "vr",
    "phone",
    "keyboard",
    "gamepad"
  ],
  "requires_vr": true,
  "shared_screen": false,
  "split_screen": false,
  "separate_screens": true,
  "turn_based": false,
  "simultaneous": true,
  "review_count": 6,
  "popularity_score_100": 46
}