{
  "title": "Wordabeasts",
  "review_score_100": 60,
  "max_players": 8,
  "platforms": [
    "Windows",
    "macOS",
    "PC"
  ],
  "review_sources": [
    "https://store.steampowered.com/app/668190/Wordabeasts/",
    "https://www.metacritic.com/game/wordabeasts"
  ],
  "notes": "Steam reviews are Mixed (65% of 20). Metacritic user score is 6.0 (4 ratings); blended score reflects mixed sentiment and small sample.",
  "raw_comment": "Word game for 3-8 players. Phones as controllers.",
  "last_updated": "2025-12-29"
}